{"cameraMode":{"drawMode":0,"name":"Shaded","section":"Shading Mode"},"sceneLighting":true,"audioPlay":false,"sceneViewState":{"showFog":true,"showMaterialUpdate":false,"showSkybox":true,"showFlares":true,"showImageEffects":true,"showParticleSystems":true},"in2DMode":false,"pivot":{"x":-0.8194847106933594,"y":-0.7711501121520996,"z":2.6539697647094728},"rotation":{"x":0.007957573980093003,"y":0.9562108516693115,"z":-0.2914060950279236,"w":0.026112083345651628},"size":28.0093936920166,"orthographic":false}